restful_wos/__init__.py
restful_wos/client.py
restful_wos/converter.py
restful_wos/extractor.py
restful_wos-0.1.dist-info/LICENSE.md
restful_wos-0.1.dist-info/METADATA
restful_wos-0.1.dist-info/WHEEL
restful_wos-0.1.dist-info/top_level.txt
restful_wos-0.1.dist-info/RECORD
