Metadata-Version: 2.1
Name: restful-wos
Version: 0.1
Summary: Python package simplifies access to the WoS RESTful API
Home-page: UNKNOWN
Author: Takuya Iwanaga
Author-email: iwanaga.takuya@anu.edu.au
License: (c) 2020 Takuya Iwanaga
Platform: UNKNOWN
Requires-Dist: pyyaml
Requires-Dist: tqdm
Requires-Dist: pebble
